Workbook

Sheet Mode d'emploi
A1: Relecture du vocabulaire coranique
A3: État du fichier
A4: Racines, fréquences et versets d'exemple : vérifiés automatiquement sur le corpus morphologique — fiables.
A5: Traductions françaises : relues une première fois, mais jamais contrôlées par un tiers. C'est l'objet de ce fichier.
A7: Colonnes à remplir — surlignées en jaune dans l'onglet « Mots »
A8: Validé ? → OK / À corriger / Douteux (liste déroulante)
A9: Correction → la traduction française corrigée, si besoin
A10: Remarque → tout commentaire libre
A12: Exemple de ligne remplie
A13: id = rabb | arabe = رَبّ | sens = Seigneur | Validé ? = À corriger | Correction = Seigneur, Maître | Remarque = préciser la nuance d'éducation
A15: Comment lire la colonne « Mots couverts »
A16: Nombre de mots du Coran que l'entrée permet de reconnaître : toute la famille de la racine pour les noms,
... A27: il faut reporter les corrections dans le fichier TypeScript, ou me redonner ce tableau pour que je le fasse.

Sheet Mots
A1: Pack | B1: N° | C1: id | D1: Arabe | E1: Translittération | F1: Sens (FR) | G1: Précision | H1: Racine | I1: Nature | J1: Mots couverts | K1: Sourate | L1: Verset | M1: Validé ? | N1: Correction | O1: Remarque
A2: Les mots de la Fâtiha | B2: 1 | C2: ism | D2: اِسْم | E2: ism | F2: nom | H2: س م و | I2: nom | J2: 381 | K2: 1 | L2: 1
A3: Les mots de la Fâtiha | B3: 1 | C3: allah | D3: اللَّه | E3: Allāh | F3: Allah | G3: Le nom propre de Dieu, jamais traduit ni mis au pluriel. | I3: nomPropre | J3: 2699 | K3: 1 | L3: 1
A4: Les mots de la Fâtiha | B4: 1 | C4: rahman | D4: الرَّحْمَٰن | E4: ar-Raḥmān | F4: le Tout Miséricordieux | G4: Miséricorde immense qui englobe toute la création, croyants et mécréants. | H4: ر ح م | I4: nom | J4: 339 | K4: 1 | L4: 3
A5: Les mots de la Fâtiha | B5: 1 | C5: rahim | D5: الرَّحِيم | E5: ar-Raḥīm | F5: le Très Miséricordieux | G5: Miséricorde constante et particulière, réservée aux croyants dans l'au-delà. | H5: ر ح م | I5: adjectif | J5: 339 | K5: 1 | L5: 3
A6: Les mots de la Fâtiha | B6: 1 | C6: hamd | D6: الْحَمْد | E6: al-ḥamd | F6: la louange | G6: Louange qui contient à la fois l'éloge et la reconnaissance. | H6: ح م د | I6: nom | J6: 68 | K6: 1 | L6: 2
A7: Les mots de la Fâtiha | B7: 1 | C7: rabb | D7: رَبّ | E7: rabb | F7: Seigneur | G7: Celui qui crée, possède, éduque et pourvoit. | H7: ر ب ب | I7: nom | J7: 980 | K7: 1 | L7: 2
A8: Les mots de la Fâtiha | B8: 1 | C8: alamin | D8: عَالَمِين | E8: ʿālamīn | F8: les mondes, les univers | H8: ع ل م | I8: nom | J8: 854 | K8: 1 | L8: 2
A9: Les mots de la Fâtiha | B9: 1 | C9: malik | D9: مَالِك | E9: mālik | F9: Maître, Souverain | H9: م ل ك | I9: nom | J9: 206 | K9: 1 | L9: 4
A10: Les mots de la Fâtiha | B10: 1 | C10: yawm | D10: يَوْم | E10: yawm | F10: jour | H10: ي و م | I10: nom | J10: 475 | K10: 1 | L10: 4
A11: Les mots de la Fâtiha | B11: 1 | C11: din | D11: دِين | E11: dīn | F11: religion, rétribution | G11: Dans « yawm ad-dīn », le sens est celui du Jugement, de la rétribution. | H11: د ي ن | I11: nom | J11: 101 | K11: 1 | L11: 4
A12: Les mots de la Fâtiha | B12: 1 | C12: abada | D12: عَبَدَ | E12: ʿabada | F12: adorer | G12: Même racine que ʿabd, le serviteur. | H12: ع ب د | I12: verbe | J12: 275 | K12: 1 | L12: 5
A13: Les mots de la Fâtiha | B13: 1 | C13: istaana | D13: اِسْتَعَانَ | E13: istaʿāna | F13: demander secours | H13: ع و ن | I13: verbe | J13: 12 | K13: 1 | L13: 5
A14: Les mots de la Fâtiha | B14: 1 | C14: hada | D14: هَدَىٰ | E14: hadā | F14: guider | H14: ه د ي | I14: verbe | J14: 316 | K14: 1 | L14: 6
A15: Les mots de la Fâtiha | B15: 1 | C15: sirat | D15: صِرَاط | E15: ṣirāṭ | F15: chemin, voie | G15: Une voie large et droite, par opposition au sentier étroit. | H15: ص ر ط | I15: nom | J15: 45 | K15: 1 | L15: 6
A16: Les mots de la Fâtiha | B16: 1 | C16: mustaqim | D16: مُسْتَقِيم | E16: mustaqīm | F16: droit, rectiligne | H16: ق و م | I16: adjectif | J16: 660 | K16: 1 | L16: 6
A17: Allah et Ses noms | B17: 2 | C17: ilah | D17: إِلَٰه | E17: ilāh | F17: divinité | G17: Nom commun : ce qui est adoré. À distinguer d'Allah, nom propre. | H17: أ ل ه | I17: nom | J17: 2851 | K17: 2 | L17: 163
A18: Allah et Ses noms | B18: 2 | C18: rahma | D18: رَحْمَة | E18: raḥma | F18: miséricorde | H18: ر ح م | I18: nom | J18: 339 | K18: 7 | L18: 156
A19: Allah et Ses noms | B19: 2 | C19: alim | D19: عَلِيم | E19: ʿalīm | F19: Omniscient | H19: ع ل م | I19: adjectif | J19: 854 | K19: 2 | L19: 32
A20: Allah et Ses noms | B20: 2 | C20: hakim | D20: حَكِيم | E20: ḥakīm | F20: Sage | H20: ح ك م | I20: adjectif | J20: 210 | K20: 2 | L20: 32
A21: Allah et Ses noms | B21: 2 | C21: aziz | D21: عَزِيز | E21: ʿazīz | F21: Puissant, Inaccessible | H21: ع ز ز | I21: adjectif | J21: 120 | K21: 2 | L21: 129
A22: Allah et Ses noms | B22: 2 | C22: ghafur | D22: غَفُور | E22: ghafūr | F22: Pardonneur | H22: غ ف ر | I22: adjectif | J22: 234 | K22: 2 | L22: 173
A23: Allah et Ses noms | B23: 2 | C23: sami | D23: سَمِيع | E23: samīʿ | F23: Audient, qui entend tout | H23: س م ع | I23: adjectif | J23: 185 | K23: 2 | L23: 127
A24: Allah et Ses noms | B24: 2 | C24: basir | D24: بَصِير | E24: baṣīr | F24: Clairvoyant, qui voit tout | H24: ب ص ر | I24: adjectif | J24: 148 | K24: 2 | L24: 96
A25: Allah et Ses noms | B25: 2 | C25: qadir | D25: قَدِير | E25: qadīr | F25: Omnipotent | H25: ق د ر | I25: adjectif | J25: 132 | K25: 2 | L25: 20
A26: Allah et Ses noms | B26: 2 | C26: khabir | D26: خَبِير | E26: khabīr | F26: Parfaitement Informé | H26: خ ب ر | I26: adjectif | J26: 52 | K26: 2 | L26: 234
A27: Allah et Ses noms | B27: 2 | C27: karim | D27: كَرِيم | E27: karīm | F27: Noble, Généreux | H27: ك ر م | I27: adjectif | J27: 47 | K27: 27 | L27: 40
A28: Allah et Ses noms | B28: 2 | C28: azim | D28: عَظِيم | E28: ʿaẓīm | F28: Immense, Grandiose | H28: ع ظ م | I28: adjectif | J28: 128 | K28: 2 | L28: 255
A29: Allah et Ses noms | B29: 2 | C29: halim | D29: حَلِيم | E29: ḥalīm | F29: Longanime, plein de mansuétude | H29: ح ل م | I29: adjectif | J29: 21 | K29: 2 | L29: 225
... A35: Allah et Ses noms | B35: 2 | C35: nur | D35: نُور | E35: nūr | F35: lumière | H35: ن و ر | I35: nom | J35: 194 | K35: 24 | L35: 35
A36: Les mots-outils essentiels | B36: 3 | C36: min | D36: مِنْ | E36: min | F36: de, depuis, parmi | I36: particule | J36: 4083 | K36: 2 | L36: 3
A37: Les mots-outils essentiels | B37: 3 | C37: ila | D37: إِلَىٰ | E37: ilā | F37: vers, jusqu'à | I37: particule | J37: 742 | K37: 2 | L37: 14
A38: Les mots-outils essentiels | B38: 3 | C38: ala | D38: عَلَىٰ | E38: ʿalā | F38: sur, contre | I38: particule | J38: 1458 | K38: 2 | L38: 5
A39: Les mots-outils essentiels | B39: 3 | C39: fi | D39: فِي | E39: fī | F39: dans, en | I39: particule | J39: 1701 | K39: 2 | L39: 10
A40: Les mots-outils essentiels | B40: 3 | C40: an | D40: عَنْ | E40: ʿan | F40: au sujet de, loin de | I40: particule | J40: 468 | K40: 2 | L40: 189
A41: Les mots-outils essentiels | B41: 3 | C41: maa | D41: مَعَ | E41: maʿa | F41: avec | I41: particule | J41: 164 | K41: 2 | L41: 153
A42: Les mots-outils essentiels | B42: 3 | C42: bayna | D42: بَيْنَ | E42: bayna | F42: entre | H42: ب ي ن | I42: particule | J42: 523 | K42: 2 | L42: 66
A43: Les mots-outils essentiels | B43: 3 | C43: inda | D43: عِنْدَ | E43: ʿinda | F43: auprès de, chez | I43: particule | J43: 197 | K43: 2 | L43: 54
A44: Les mots-outils essentiels | B44: 3 | C44: baada | D44: بَعْدَ | E44: baʿda | F44: après | H44: ب ع د | I44: particule | J44: 235 | K44: 2 | L44: 27
A45: Les mots-outils essentiels | B45: 3 | C45: qabla | D45: قَبْلَ | E45: qabla | F45: avant | H45: ق ب ل | I45: particule | J45: 294 | K45: 2 | L45: 25
A46: Les mots-outils essentiels | B46: 3 | C46: ladun | D46: لَدُنْ | E46: ladun | F46: d'auprès de | G46: Insiste sur l'origine directe : « de la part même de ». | I46: particule | J46: 18 | K46: 18 | L46: 65
A47: Les mots-outils essentiels | B47: 3 | C47: duna | D47: دُونَ | E47: dūna | F47: en dehors de, à l'exclusion de | G47: Très fréquent dans « min dūni-llāh » : en dehors d'Allah. | H47: د و ن | I47: particule | J47: 144 | K47: 2 | L47: 23
A48: Les mots-outils essentiels | B48: 3 | C48: fawqa | D48: فَوْقَ | E48: fawqa | F48: au-dessus de | H48: ف و ق | I48: particule | J48: 43 | K48: 2 | L48: 26
A49: Les mots-outils essentiels | B49: 3 | C49: tahta | D49: تَحْتَ | E49: taḥta | F49: sous, en dessous de | H49: ت ح ت | I49: particule | J49: 51 | K49: 2 | L49: 25
A50: Les mots-outils essentiels | B50: 3 | C50: mithl | D50: مِثْل | E50: mithl | F50: semblable à, comme | H50: م ث ل | I50: nom | J50: 169 | K50: 2 | L50: 23
A51: Les mots-outils essentiels | B51: 3 | C51: illa | D51: إِلَّا | E51: illā | F51: sauf, si ce n'est | G51: Charnière de l'attestation de foi : « nulle divinité si ce n'est Lui ». | I51: particule | J51: 698 | K51: 2 | L51: 9
A52: Les mots-outils essentiels | B52: 3 | C52: hatta | D52: حَتَّىٰ | E52: ḥattā | F52: jusqu'à ce que | I52: particule | J52: 142 | K52: 2 | L52: 109
A53: Les mots-outils essentiels | B53: 3 | C53: laalla | D53: لَعَلَّ | E53: laʿalla | F53: afin que, peut-être | G53: Introduit presque toujours une finalité : « afin que vous soyez reconnaissants ». | I53: particule | J53: 129 | K53: 2 | L53: 21
A54: Les mots-outils essentiels | B54: 3 | C54: kama | D54: كَمَا | E54: kamā | F54: de même que, comme | I54: particule | J54: 58 | K54: 2 | L54: 13
A55: Les grands verbes | B55: 4 | C55: qala | D55: قَالَ | E55: qāla | F55: dire | G55: Le verbe le plus fréquent du Coran : il ouvre presque tous les dialogues. | H55: ق و ل | I55: verbe | J55: 1722 | K55: 2 | L55: 30
A56: Les grands verbes | B56: 4 | C56: kana | D56: كَانَ | E56: kāna | F56: être, avoir été | H56: ك و ن | I56: verbe | J56: 1390 | K56: 2 | L56: 34
A57: Les grands verbes | B57: 4 | C57: jaala | D57: جَعَلَ | E57: jaʿala | F57: faire de, établir, placer | H57: ج ع ل | I57: verbe | J57: 346 | K57: 2 | L57: 22
A58: Les grands verbes | B58: 4 | C58: alima | D58: عَلِمَ | E58: ʿalima | F58: savoir, connaître | H58: ع ل م | I58: verbe | J58: 854 | K58: 2 | L58: 30
A59: Les grands verbes | B59: 4 | C59: khalaqa | D59: خَلَقَ | E59: khalaqa | F59: créer | H59: خ ل ق | I59: verbe | J59: 261 | K59: 2 | L59: 21
A60: Les grands verbes | B60: 4 | C60: ata | D60: أَتَىٰ | E60: atā | F60: venir, survenir | H60: أ ت ي | I60: verbe | J60: 549 | K60: 16 | L60: 1
A61: Les grands verbes | B61: 4 | C61: jaa | D61: جَاءَ | E61: jāʾa | F61: venir, arriver | H61: ج ي أ | I61: verbe | J61: 278 | K61: 2 | L61: 87
A62: Les grands verbes | B62: 4 | C62: faala | D62: فَعَلَ | E62: faʿala | F62: faire, accomplir | H62: ف ع ل | I62: verbe | J62: 108 | K62: 2 | L62: 24
A63: Les grands verbes | B63: 4 | C63: amila | D63: عَمِلَ | E63: ʿamila | F63: œuvrer, agir | G63: Désigne l'acte concret, souvent associé à « ṣāliḥ » : les bonnes œuvres. | H63: ع م ل | I63: verbe | J63: 360 | K63: 2 | L63: 25
A64: Les grands verbes | B64: 4 | C64: arada | D64: أَرَادَ | E64: arāda | F64: vouloir, désirer | H64: ر و د | I64: verbe | J64: 148 | K64: 2 | L64: 26
A65: Les grands verbes | B65: 4 | C65: raa | D65: رَأَىٰ | E65: raʾā | F65: voir, considérer | H65: ر أ ي | I65: verbe | J65: 328 | K65: 2 | L65: 55
A66: Les grands verbes | B66: 4 | C66: samia | D66: سَمِعَ | E66: samiʿa | F66: entendre, écouter | H66: س م ع | I66: verbe | J66: 185 | K66: 2 | L66: 93
A67: Les grands verbes | B67: 4 | C67: wajada | D67: وَجَدَ | E67: wajada | F67: trouver | H67: و ج د | I67: verbe | J67: 107 | K67: 4 | L67: 43
A68: Les grands verbes | B68: 4 | C68: akhadha | D68: أَخَذَ | E68: akhadha | F68: prendre, saisir | H68: أ خ ذ | I68: verbe | J68: 273 | K68: 2 | L68: 55
A69: Les grands verbes | B69: 4 | C69: akhraja | D69: أَخْرَجَ | E69: akhraja | F69: faire sortir, expulser | H69: خ ر ج | I69: verbe | J69: 182 | K69: 2 | L69: 22
A70: Les grands verbes | B70: 4 | C70: dakhala | D70: دَخَلَ | E70: dakhala | F70: entrer | H70: د خ ل | I70: verbe | J70: 126 | K70: 2 | L70: 58
A71: Les grands verbes | B71: 4 | C71: nazala | D71: نَزَلَ | E71: nazala | F71: descendre | G71: À la forme dérivée « anzala » : faire descendre, révéler. | H71: ن ز ل | I71: verbe | J71: 293 | K71: 2 | L71: 4
A72: Les grands verbes | B72: 4 | C72: kataba | D72: كَتَبَ | E72: kataba | F72: écrire, prescrire | H72: ك ت ب | I72: verbe | J72: 319 | K72: 2 | L72: 183
A73: Les grands verbes | B73: 4 | C73: amara | D73: أَمَرَ | E73: amara | F73: ordonner, commander | H73: أ م ر | I73: verbe | J73: 248 | K73: 2 | L73: 27
A74: Les grands verbes | B74: 4 | C74: baatha | D74: بَعَثَ | E74: baʿatha | F74: envoyer, ressusciter | H74: ب ع ث | I74: verbe | J74: 67 | K74: 2 | L74: 56
A75: Les grands verbes | B75: 4 | C75: rajaa | D75: رَجَعَ | E75: rajaʿa | F75: revenir, retourner | H75: ر ج ع | I75: verbe | J75: 104 | K75: 2 | L75: 18
A76: Les grands verbes | B76: 4 | C76: daraba | D76: ضَرَبَ | E76: ḍaraba | F76: frapper, proposer (un exemple) | G76: « ḍaraba mathalan » : proposer une parabole. Sens très différent du sens propre. | H76: ض ر ب | I76: verbe | J76: 58 | K76: 2 | L76: 26
A77: Les grands verbes | B77: 4 | C77: nazara | D77: نَظَرَ | E77: naẓara | F77: regarder, observer | H77: ن ظ ر | I77: verbe | J77: 129 | K77: 2 | L77: 50
A78: La foi et la mécréance | B78: 5 | C78: amana | D78: آمَنَ | E78: āmana | F78: croire, avoir foi | G78: Même racine que « amn », la sécurité : croire, c'est se mettre en sécurité. | H78: أ م ن | I78: verbe | J78: 879 | K78: 2 | L78: 3
A79: La foi et la mécréance | B79: 5 | C79: iman | D79: إِيمَان | E79: īmān | F79: la foi | H79: أ م ن | I79: nom | J79: 879 | K79: 49 | L79: 7
A80: La foi et la mécréance | B80: 5 | C80: mumin | D80: مُؤْمِن | E80: muʾmin | F80: croyant | H80: أ م ن | I80: nom | J80: 879 | K80: 2 | L80: 221
A81: La foi et la mécréance | B81: 5 | C81: kafara | D81: كَفَرَ | E81: kafara | F81: mécroire, renier | G81: Sens premier de la racine : recouvrir, dissimuler — donc couvrir la vérité. | H81: ك ف ر | I81: verbe | J81: 525 | K81: 2 | L81: 6
A82: La foi et la mécréance | B82: 5 | C82: kafir | D82: كَافِر | E82: kāfir | F82: mécréant, négateur | H82: ك ف ر | I82: nom | J82: 525 | K82: 2 | L82: 19
A83: La foi et la mécréance | B83: 5 | C83: ashraka | D83: أَشْرَكَ | E83: ashraka | F83: associer (à Allah) | H83: ش ر ك | I83: verbe | J83: 168 | K83: 6 | L83: 151
A84: La foi et la mécréance | B84: 5 | C84: mushrik | D84: مُشْرِك | E84: mushrik | F84: associateur, polythéiste | H84: ش ر ك | I84: nom | J84: 168 | K84: 9 | L84: 5
A85: La foi et la mécréance | B85: 5 | C85: munafiq | D85: مُنَافِق | E85: munāfiq | F85: hypocrite | H85: ن ف ق | I85: nom | J85: 111 | K85: 4 | L85: 138
A86: La foi et la mécréance | B86: 5 | C86: shahida | D86: شَهِدَ | E86: shahida | F86: témoigner, attester | H86: ش ه د | I86: verbe | J86: 160 | K86: 3 | L86: 18
A87: La foi et la mécréance | B87: 5 | C87: sadaqa | D87: صَدَقَ | E87: ṣadaqa | F87: dire vrai, être véridique | H87: ص د ق | I87: verbe | J87: 155 | K87: 2 | L87: 23
A88: La foi et la mécréance | B88: 5 | C88: kadhdhaba | D88: كَذَّبَ | E88: kadhdhaba | F88: démentir, traiter de mensonge | H88: ك ذ ب | I88: verbe | J88: 282 | K88: 55 | L88: 13
A89: La foi et la mécréance | B89: 5 | C89: taba | D89: تَابَ | E89: tāba | F89: se repentir, revenir | H89: ت و ب | I89: verbe | J89: 87 | K89: 2 | L89: 37
A90: La foi et la mécréance | B90: 5 | C90: istaghfara | D90: اِسْتَغْفَرَ | E90: istaghfara | F90: demander pardon | H90: غ ف ر | I90: verbe | J90: 234 | K90: 71 | L90: 10
A91: La foi et la mécréance | B91: 5 | C91: tawakkala | D91: تَوَكَّلَ | E91: tawakkala | F91: s'en remettre (à Allah) | H91: و ك ل | I91: verbe | J91: 70 | K91: 3 | L91: 159
A92: La foi et la mécréance | B92: 5 | C92: khafa | D92: خَافَ | E92: khāfa | F92: craindre, avoir peur | H92: خ و ف | I92: verbe | J92: 124 | K92: 2 | L92: 38
A93: La foi et la mécréance | B93: 5 | C93: khashiya | D93: خَشِيَ | E93: khashiya | F93: redouter (avec révérence) | G93: Crainte mêlée de respect, réservée surtout à Allah — plus forte que khāfa. | H93: خ ش ي | I93: verbe | J93: 48 | K93: 2 | L93: 74
A94: La foi et la mécréance | B94: 5 | C94: ittaqa | D94: اِتَّقَىٰ | E94: ittaqā | F94: craindre Allah, se prémunir | H94: و ق ي | I94: verbe | J94: 258 | K94: 2 | L94: 2
A95: La foi et la mécréance | B95: 5 | C95: taqwa | D95: تَقْوَىٰ | E95: taqwā | F95: piété, crainte révérencielle | H95: و ق ي | I95: nom | J95: 258 | K95: 2 | L95: 197
A96: La foi et la mécréance | B96: 5 | C96: muttaqin | D96: مُتَّقِين | E96: muttaqīn | F96: les pieux, ceux qui craignent Allah | H96: و ق ي | I96: nom | J96: 258 | K96: 2 | L96: 2
A97: Le Livre et la révélation | B97: 6 | C97: kitab | D97: كِتَاب | E97: kitāb | F97: Livre, Écriture | G97: Désigne le Livre révélé, mais aussi l'écrit et le registre où sont consignés les actes. | H97: ك ت ب | I97: nom | J97: 319 | K97: 2 | L97: 2
A98: Le Livre et la révélation | B98: 6 | C98: quran | D98: قُرْآن | E98: qurʾān | F98: Coran, récitation | G98: Littéralement « ce qui est récité », de la racine qaraʾa : lire à voix haute. | H98: ق ر أ | I98: nom | J98: 88 | K98: 2 | L98: 185
A99: Le Livre et la révélation | B99: 6 | C99: aya | D99: آيَة | E99: āya | F99: signe, verset, prodige | G99: Un même mot pour le verset du Livre et le signe dans la création. | H99: أ ي ي | I99: nom | J99: 597 | K99: 2 | L99: 106
A100: Le Livre et la révélation | B100: 6 | C100: anzala | D100: أَنْزَلَ | E100: anzala | F100: faire descendre, révéler | H100: ن ز ل | I100: verbe | J100: 293 | K100: 2 | L100: 4
A101: Le Livre et la révélation | B101: 6 | C101: wahy | D101: وَحْي | E101: waḥy | F101: révélation, inspiration | H101: و ح ي | I101: nom | J101: 78 | K101: 53 | L101: 4
A102: Le Livre et la révélation | B102: 6 | C102: dhikr | D102: ذِكْر | E102: dhikr | F102: rappel, évocation | G102: Le rappel et l'évocation — et l'un des noms que le Coran se donne à lui-même. | H102: ذ ك ر | I102: nom | J102: 292 | K102: 15 | L102: 9
A103: Le Livre et la révélation | B103: 6 | C103: dhakara | D103: ذَكَرَ | E103: dhakara | F103: évoquer, mentionner, se souvenir | H103: ذ ك ر | I103: verbe | J103: 292 | K103: 2 | L103: 152
A104: Le Livre et la révélation | B104: 6 | C104: tala | D104: تَلَا | E104: talā | F104: réciter, suivre | H104: ت ل و | I104: verbe | J104: 63 | K104: 2 | L104: 102
A105: Le Livre et la révélation | B105: 6 | C105: qaraa | D105: قَرَأَ | E105: qaraʾa | F105: lire, réciter | H105: ق ر أ | I105: verbe | J105: 88 | K105: 96 | L105: 1
...

Sheet Synthèse
A1: Avancement de la relecture
A3: Total de mots | B3: =COUNTA(Mots!C2:C368) -> 367
A4: Relus | B4: =COUNTA(Mots!M2:M368) -> 0
A5: Restants | B5: =B3-B4 -> 367
A6: Avancement | B6: =IF(B3=0,0,B4/B3) -> 0
A8: OK | B8: =COUNTIF(Mots!M2:M368,"OK") -> 0
A9: À corriger | B9: =COUNTIF(Mots!M2:M368,"À corriger") -> 0
A10: Douteux | B10: =COUNTIF(Mots!M2:M368,"Douteux") -> 0
A11: Avec précision | B11: =COUNTA(Mots!G2:G368) -> 82
A13: Rentabilité par pack — total des mots du Coran couverts
A14: Pack | B14: Mots | C14: Relus | D14: Mots couverts
A15: Les mots de la Fâtiha | B15: =COUNTIF(Mots!$A$2:$A$368,A15) -> 15 | C15: =COUNTIFS(Mots!$A$2:$A$368,A15,Mots!$M$2:$M$368,"<>") -> 0 | D15: =SUMIF(Mots!$A$2:$A$368,A15,Mots!$J$2:$J$368) -> 7750
A16: Allah et Ses noms | B16: =COUNTIF(Mots!$A$2:$A$368,A16) -> 19 | C16: =COUNTIFS(Mots!$A$2:$A$368,A16,Mots!$M$2:$M$368,"<>") -> 0 | D16: =SUMIF(Mots!$A$2:$A$368,A16,Mots!$J$2:$J$368) -> 6594
A17: Les mots-outils essentiels | B17: =COUNTIF(Mots!$A$2:$A$368,A17) -> 19 | C17: =COUNTIFS(Mots!$A$2:$A$368,A17,Mots!$M$2:$M$368,"<>") -> 0 | D17: =SUMIF(Mots!$A$2:$A$368,A17,Mots!$J$2:$J$368) -> 11317
A18: Les grands verbes | B18: =COUNTIF(Mots!$A$2:$A$368,A18) -> 23 | C18: =COUNTIFS(Mots!$A$2:$A$368,A18,Mots!$M$2:$M$368,"<>") -> 0 | D18: =SUMIF(Mots!$A$2:$A$368,A18,Mots!$J$2:$J$368) -> 8435
A19: La foi et la mécréance | B19: =COUNTIF(Mots!$A$2:$A$368,A19) -> 19 | C19: =COUNTIFS(Mots!$A$2:$A$368,A19,Mots!$M$2:$M$368,"<>") -> 0 | D19: =SUMIF(Mots!$A$2:$A$368,A19,Mots!$J$2:$J$368) -> 6068
A20: Le Livre et la révélation | B20: =COUNTIF(Mots!$A$2:$A$368,A20) -> 17 | C20: =COUNTIFS(Mots!$A$2:$A$368,A20,Mots!$M$2:$M$368,"<>") -> 0 | D20: =SUMIF(Mots!$A$2:$A$368,A20,Mots!$J$2:$J$368) -> 4573
A21: Pronoms et démonstratifs | B21: =COUNTIF(Mots!$A$2:$A$368,A21) -> 18 | C21: =COUNTIFS(Mots!$A$2:$A$368,A21,Mots!$M$2:$M$368,"<>") -> 0 | D21: =SUMIF(Mots!$A$2:$A$368,A21,Mots!$J$2:$J$368) -> 11192
A22: L'au-delà : Paradis et Enfer | B22: =COUNTIF(Mots!$A$2:$A$368,A22) -> 21 | C22: =COUNTIFS(Mots!$A$2:$A$368,A22,Mots!$M$2:$M$368,"<>") -> 0 | D22: =SUMIF(Mots!$A$2:$A$368,A22,Mots!$J$2:$J$368) -> 3540
A23: Le ciel, la terre et la création | B23: =COUNTIF(Mots!$A$2:$A$368,A23) -> 20 | C23: =COUNTIFS(Mots!$A$2:$A$368,A23,Mots!$M$2:$M$368,"<>") -> 0 | D23: =SUMIF(Mots!$A$2:$A$368,A23,Mots!$J$2:$J$368) -> 2126
A24: Négations, conditions et liaisons | B24: =COUNTIF(Mots!$A$2:$A$368,A24) -> 19 | C24: =COUNTIFS(Mots!$A$2:$A$368,A24,Mots!$M$2:$M$368,"<>") -> 0 | D24: =SUMIF(Mots!$A$2:$A$368,A24,Mots!$J$2:$J$368) -> 14995
A25: L'homme : corps et âme | B25: =COUNTIF(Mots!$A$2:$A$368,A25) -> 16 | C25: =COUNTIFS(Mots!$A$2:$A$368,A25,Mots!$M$2:$M$368,"<>") -> 0 | D25: =SUMIF(Mots!$A$2:$A$368,A25,Mots!$J$2:$J$368) -> 1429
A26: Le bien, le mal et la piété | B26: =COUNTIF(Mots!$A$2:$A$368,A26) -> 21 | C26: =COUNTIFS(Mots!$A$2:$A$368,A26,Mots!$M$2:$M$368,"<>") -> 0 | D26: =SUMIF(Mots!$A$2:$A$368,A26,Mots!$J$2:$J$368) -> 3064
... A34: Verbes du récit | B34: =COUNTIF(Mots!$A$2:$A$368,A34) -> 20 | C34: =COUNTIFS(Mots!$A$2:$A$368,A34,Mots!$M$2:$M$368,"<>") -> 0 | D34: =SUMIF(Mots!$A$2:$A$368,A34,Mots!$J$2:$J$368) -> 1575
A36: Ne pas additionner la colonne « Mots couverts » : deux mots d'une même racine couvrent les mêmes occurrences. Elle sert à classer les packs, pas à totaliser. La couverture réelle est de 76,7 %.
